src/__init__.py
src/main.py
src/model/__init__.py
src/model/fsm.py
fsmlog-1.0.0.dist-info/LICENSE
fsmlog-1.0.0.dist-info/METADATA
fsmlog-1.0.0.dist-info/WHEEL
fsmlog-1.0.0.dist-info/entry_points.txt
fsmlog-1.0.0.dist-info/top_level.txt
fsmlog-1.0.0.dist-info/RECORD
