Metadata-Version: 2.1
Name: fsmlog
Version: 1.0.0
Summary: A tool for converting finite state machine to verilog code
Home-page: https://github.com/Parsa2820/fsmlog
Author: Parsa Mohammadian
Author-email: parsa2820@gmail.com
Requires-Python: >=3.5
License-File: LICENSE
Requires-Dist: typer
Requires-Dist: Jinja2
Requires-Dist: dacite
